layg/__init__.py
layg/learner.py
layg/util.py
layg/emulator/__init__.py
layg/emulator/cholesky_nn_emulator.py
layg/emulator/emulator.py
layg/emulator/interpolation_emulator.py
layg/emulator/nn.py
layg/emulator/torch_emulator.py
layg-0.0.2.dist-info/LICENSE
layg-0.0.2.dist-info/METADATA
layg-0.0.2.dist-info/WHEEL
layg-0.0.2.dist-info/top_level.txt
layg-0.0.2.dist-info/RECORD
