Metadata-Version: 2.1
Name: layg
Version: 0.0.2
Summary: Learn-as-you-go emulator with error estimation
Home-page: https://github.com/auckland-cosmo/LearnAsYouGoEmulator
Author: Nathan Musoke, Layne Price
Author-email: n.musoke@aucland.ac.nz, layne.c.price@gmail.com
License: Apache Licence (2.0)
Classifier: Programming Language :: Python :: 3
Classifier: License :: OSI Approved :: Apache Software License
Classifier: Intended Audience :: Science/Research
Classifier: Operating System :: OS Independent
Classifier: Topic :: Scientific/Engineering :: Artificial Intelligence
Classifier: Topic :: Scientific/Engineering :: Astronomy
Classifier: Topic :: Scientific/Engineering :: Physics
Requires-Python: >=3.5
License-File: LICENSE
Requires-Dist: matplotlib
Requires-Dist: numpy
Requires-Dist: numpydoc
Requires-Dist: torch
Requires-Dist: scipy
Requires-Dist: sphinx
Requires-Dist: sphinx-rtd-theme
Requires-Dist: emcee (<3,>=2)
Requires-Dist: gif (==1.0.3)
